{"season": "20032004", "gameType": 2, "skaters": [{"playerId": 8445575, "headshot": "https://assets.nhle.com/mugs/nhl/20032004/OTT/8445575.png", "firstName": {"default": "Peter"}, "lastName": {"default": "Bondra"}, "positionCode": "R", "gamesPlayed": 23, "goals": 5, "assists": 9, "points": 14, "plusMinus": 1, "penaltyMinutes": 16, "powerPlayGoals": 2, "shorthandedGoals": 0, "gameWinningGoals": 1, "overtimeGoals": 0, "shots": 52, "shootingPctg": 0.0962, "avgTimeOnIcePerGame": 1101.4348, "avgShiftsPerGame": 23.9, "faceoffWinPctg": 0.0}, {"playerId": 8448092, "headshot": "https://assets.nhle.com/mugs/nhl/20032004/OTT/8448092.png", "firstName": {"default": "Jody"}, "lastName": {"default": "Hull"}, "positionCode": "R", "gamesPlayed": 1, "goals": 0, "assists": 0, "points": 0, "plusMinus": 0, "penaltyMinutes": 0, "powerPlayGoals": 0, "shorthandedGoals": 0, "gameWinningGoals": 0, "overtimeGoals": 0, "shots": 0, "shootingPctg": 0.0, "avgTimeOnIcePerGame": 171.0, "avgShiftsPerGame": 4.0, "faceoffWinPctg": 0.0}, {"playerId": 8448797, "headshot": "https://assets.nhle.com/mugs/nhl/20032004/OTT/8448797.png", "firstName": {"default": "Curtis"}, "lastName": {"default": "Leschyshyn"}, "positionCode": "D", "gamesPlayed": 56, "goals": 1, "assists": 4, "points": 5, "plusMinus": 13, "penaltyMinutes": 16, "powerPlayGoals": 0, "shorthandedGoals": 0, "gameWinningGoals": 0, "overtimeGoals": 0, "shots": 30, "shootingPctg": 0.0333, "avgTimeOnIcePerGame": 834.0893, "avgShiftsPerGame": 20.2, "faceoffWinPctg": 0.0}, {"playerId": 8450678, "headshot": "https://assets.nhle.com/mugs/nhl/20032004/OTT/8450678.png", "firstName": {"default": "Rob"}, "lastName": {"default": "Ray"}, "positionCode": "R", "gamesPlayed": 6, "goals": 1, "assists": 0, "points": 1, "plusMinus": 0, "penaltyMinutes": 14, "powerPlayGoals": 0, "shorthandedGoals": 0, "gameWinningGoals": 0, "overtimeGoals": 0, "shots": 3, "shootingPctg": 0.3333, "avgTimeOnIcePerGame": 279.5, "avgShiftsPerGame": 7.3, "faceoffWinPctg": 0.0}, {"playerId": 8452147, "headshot": "https://assets.nhle.com/mugs/nhl/20032004/OTT/8452147.png", "firstName": {"default": "Shaun"}, "lastName": {"default": "Van Allen"}, "positionCode": "C", "gamesPlayed": 73, "goals": 2, "assists": 10, "points": 12, "plusMinus": 6, "penaltyMinutes": 80, "powerPlayGoals": 0, "shorthandedGoals": 1, "gameWinningGoals": 0, "overtimeGoals": 0, "shots": 41, "shootingPctg": 0.0488, "avgTimeOnIcePerGame": 689.4384, "avgShiftsPerGame": 17.7, "faceoffWinPctg": 0.5227}, {"playerId": 8458069, "headshot": "https://assets.nhle.com/mugs/nhl/20032004/OTT/8458069.png", "firstName": {"default": "Bryan"}, "lastName": {"default": "Smolinski"}, "positionCode": "C", "gamesPlayed": 80, "goals": 19, "assists": 27, "points": 46, "plusMinus": 22, "penaltyMinutes": 49, "powerPlayGoals": 4, "shorthandedGoals": 0, "gameWinningGoals": 3, "overtimeGoals": 0, "shots": 182, "shootingPctg": 0.1044, "avgTimeOnIcePerGame": 999.275, "avgShiftsPerGame": 23.5, "faceoffWinPctg": 0.4466}, {"playerId": 8460105, "headshot": "https://assets.nhle.com/mugs/nhl/20032004/OTT/8460105.png", "firstName": {"default": "Radek"}, "lastName": {"default": "Bonk"}, "positionCode": "C", "gamesPlayed": 66, "goals": 12, "assists": 32, "points": 44, "plusMinus": 2, "penaltyMinutes": 66, "powerPlayGoals": 6, "shorthandedGoals": 0, "gameWinningGoals": 1, "overtimeGoals": 0, "shots": 98, "shootingPctg": 0.1224, "avgTimeOnIcePerGame": 1057.7273, "avgShiftsPerGame": 23.7, "faceoffWinPctg": 0.4493}, {"playerId": 8460254, "headshot": "https://assets.nhle.com/mugs/nhl/20032004/OTT/8460254.png", "firstName": {"default": "Greg"}, "lastName": {"default": "De Vries"}, "positionCode": "D", "gamesPlayed": 13, "goals": 0, "assists": 1, "points": 1, "plusMinus": 0, "penaltyMinutes": 6, "powerPlayGoals": 0, "shorthandedGoals": 0, "gameWinningGoals": 0, "overtimeGoals": 0, "shots": 12, "shootingPctg": 0.0, "avgTimeOnIcePerGame": 1071.2308, "avgShiftsPerGame": 24.8, "faceoffWinPctg": 0.0}, {"playerId": 8460579, "headshot": "https://assets.nhle.com/mugs/nhl/20032004/OTT/8460579.png", "firstName": {"default": "Vaclav"}, "lastName": {"default": "Varada", "cs": "Vara\u010fa"}, "positionCode": "R", "gamesPlayed": 30, "goals": 5, "assists": 5, "points": 10, "plusMinus": 2, "penaltyMinutes": 26, "powerPlayGoals": 0, "shorthandedGoals": 0, "gameWinningGoals": 1, "overtimeGoals": 0, "shots": 47, "shootingPctg": 0.1064, "avgTimeOnIcePerGame": 860.5667, "avgShiftsPerGame": 20.2, "faceoffWinPctg": 0.3571}, {"playerId": 8460621, "headshot": "https://assets.nhle.com/mugs/nhl/20032004/OTT/8460621.png", "firstName": {"default": "Daniel"}, "lastName": {"default": "Alfredsson"}, "positionCode": "R", "gamesPlayed": 77, "goals": 32, "assists": 48, "points": 80, "plusMinus": 12, "penaltyMinutes": 24, "powerPlayGoals": 9, "shorthandedGoals": 0, "gameWinningGoals": 5, "overtimeGoals": 0, "shots": 230, "shootingPctg": 0.1391, "avgTimeOnIcePerGame": 1164.3247, "avgShiftsPerGame": 23.8, "faceoffWinPctg": 0.2424}, {"playerId": 8460661, "headshot": "https://assets.nhle.com/mugs/nhl/20032004/OTT/8460661.png", "firstName": {"default": "Shane"}, "lastName": {"default": "Hnidy"}, "positionCode": "D", "gamesPlayed": 37, "goals": 0, "assists": 5, "points": 5, "plusMinus": 2, "penaltyMinutes": 72, "powerPlayGoals": 0, "shorthandedGoals": 0, "gameWinningGoals": 0, "overtimeGoals": 0, "shots": 16, "shootingPctg": 0.0, "avgTimeOnIcePerGame": 679.027, "avgShiftsPerGame": 17.6, "faceoffWinPctg": 0.0}, {"playerId": 8460782, "headshot": "https://assets.nhle.com/mugs/nhl/20032004/OTT/8460782.png", "firstName": {"default": "Todd"}, "lastName": {"default": "Simpson"}, "positionCode": "D", "gamesPlayed": 16, "goals": 0, "assists": 1, "points": 1, "plusMinus": -1, "penaltyMinutes": 47, "powerPlayGoals": 0, "shorthandedGoals": 0, "gameWinningGoals": 0, "overtimeGoals": 0, "shots": 10, "shootingPctg": 0.0, "avgTimeOnIcePerGame": 861.125, "avgShiftsPerGame": 19.9, "faceoffWinPctg": 0.0}, {"playerId": 8462033, "headshot": "https://assets.nhle.com/mugs/nhl/20032004/OTT/8462033.png", "firstName": {"default": "Wade"}, "lastName": {"default": "Redden"}, "positionCode": "D", "gamesPlayed": 81, "goals": 17, "assists": 26, "points": 43, "plusMinus": 21, "penaltyMinutes": 65, "powerPlayGoals": 12, "shorthandedGoals": 0, "gameWinningGoals": 3, "overtimeGoals": 0, "shots": 175, "shootingPctg": 0.0971, "avgTimeOnIcePerGame": 1494.3704, "avgShiftsPerGame": 31.2, "faceoffWinPctg": 0.0}, {"playerId": 8462093, "headshot": "https://assets.nhle.com/mugs/nhl/20032004/OTT/8462093.png", "firstName": {"default": "Peter"}, "lastName": {"default": "Schaefer"}, "positionCode": "L", "gamesPlayed": 81, "goals": 15, "assists": 24, "points": 39, "plusMinus": 22, "penaltyMinutes": 26, "powerPlayGoals": 2, "shorthandedGoals": 2, "gameWinningGoals": 3, "overtimeGoals": 0, "shots": 112, "shootingPctg": 0.1339, "avgTimeOnIcePerGame": 936.0494, "avgShiftsPerGame": 21.6, "faceoffWinPctg": 0.2308}, {"playerId": 8462185, "headshot": "https://assets.nhle.com/mugs/nhl/20032004/OTT/8462185.png", "firstName": {"default": "Denis"}, "lastName": {"default": "Hamel"}, "positionCode": "L", "gamesPlayed": 5, "goals": 0, "assists": 0, "points": 0, "plusMinus": -3, "penaltyMinutes": 0, "powerPlayGoals": 0, "shorthandedGoals": 0, "gameWinningGoals": 0, "overtimeGoals": 0, "shots": 6, "shootingPctg": 0.0, "avgTimeOnIcePerGame": 376.4, "avgShiftsPerGame": 9.6, "faceoffWinPctg": 1.0}, {"playerId": 8464956, "headshot": "https://assets.nhle.com/mugs/nhl/20032004/OTT/8464956.png", "firstName": {"default": "Chris"}, "lastName": {"default": "Phillips"}, "positionCode": "D", "gamesPlayed": 82, "goals": 7, "assists": 16, "points": 23, "plusMinus": 15, "penaltyMinutes": 46, "powerPlayGoals": 0, "shorthandedGoals": 0, "gameWinningGoals": 1, "overtimeGoals": 1, "shots": 93, "shootingPctg": 0.0753, "avgTimeOnIcePerGame": 1250.4878, "avgShiftsPerGame": 28.3, "faceoffWinPctg": 1.0}, {"playerId": 8465009, "headshot": "https://assets.nhle.com/mugs/nhl/20032004/OTT/8465009.png", "firstName": {"default": "Zdeno"}, "lastName": {"default": "Chara", "cs": "Ch\u00e1ra", "sk": "Ch\u00e1ra"}, "positionCode": "D", "gamesPlayed": 79, "goals": 16, "assists": 25, "points": 41, "plusMinus": 33, "penaltyMinutes": 147, "powerPlayGoals": 7, "shorthandedGoals": 0, "gameWinningGoals": 3, "overtimeGoals": 0, "shots": 185, "shootingPctg": 0.0865, "avgTimeOnIcePerGame": 1477.8608, "avgShiftsPerGame": 31.0, "faceoffWinPctg": 0.0}, {"playerId": 8466148, "headshot": "https://assets.nhle.com/mugs/nhl/20032004/OTT/8466148.png", "firstName": {"default": "Marian"}, "lastName": {"default": "Hossa"}, "positionCode": "R", "gamesPlayed": 81, "goals": 36, "assists": 46, "points": 82, "plusMinus": 4, "penaltyMinutes": 46, "powerPlayGoals": 14, "shorthandedGoals": 1, "gameWinningGoals": 5, "overtimeGoals": 0, "shots": 233, "shootingPctg": 0.1545, "avgTimeOnIcePerGame": 1117.4321, "avgShiftsPerGame": 24.8, "faceoffWinPctg": 0.4}, {"playerId": 8466200, "headshot": "https://assets.nhle.com/mugs/nhl/20032004/OTT/8466200.png", "firstName": {"default": "Josh"}, "lastName": {"default": "Langfeld"}, "positionCode": "R", "gamesPlayed": 38, "goals": 7, "assists": 10, "points": 17, "plusMinus": 6, "penaltyMinutes": 16, "powerPlayGoals": 2, "shorthandedGoals": 0, "gameWinningGoals": 2, "overtimeGoals": 0, "shots": 59, "shootingPctg": 0.1186, "avgTimeOnIcePerGame": 653.2105, "avgShiftsPerGame": 16.3, "faceoffWinPctg": 0.8}, {"playerId": 8466353, "headshot": "https://assets.nhle.com/mugs/nhl/20032004/OTT/8466353.png", "firstName": {"default": "Karel"}, "lastName": {"default": "Rachunek", "cs": "Rach\u016fnek"}, "positionCode": "D", "gamesPlayed": 60, "goals": 1, "assists": 16, "points": 17, "plusMinus": 17, "penaltyMinutes": 29, "powerPlayGoals": 0, "shorthandedGoals": 0, "gameWinningGoals": 0, "overtimeGoals": 0, "shots": 99, "shootingPctg": 0.0101, "avgTimeOnIcePerGame": 1183.1167, "avgShiftsPerGame": 26.9, "faceoffWinPctg": 0.0}, {"playerId": 8466392, "headshot": "https://assets.nhle.com/mugs/nhl/20032004/OTT/8466392.png", "firstName": {"default": "Todd"}, "lastName": {"default": "White"}, "positionCode": "C", "gamesPlayed": 53, "goals": 9, "assists": 20, "points": 29, "plusMinus": 12, "penaltyMinutes": 22, "powerPlayGoals": 1, "shorthandedGoals": 1, "gameWinningGoals": 2, "overtimeGoals": 1, "shots": 98, "shootingPctg": 0.0918, "avgTimeOnIcePerGame": 1051.8302, "avgShiftsPerGame": 24.3, "faceoffWinPctg": 0.5199}, {"playerId": 8466421, "headshot": "https://assets.nhle.com/mugs/nhl/20032004/OTT/8466421.png", "firstName": {"default": "Serge"}, "lastName": {"default": "Payer"}, "positionCode": "C", "gamesPlayed": 5, "goals": 0, "assists": 1, "points": 1, "plusMinus": 1, "penaltyMinutes": 2, "powerPlayGoals": 0, "shorthandedGoals": 0, "gameWinningGoals": 0, "overtimeGoals": 0, "shots": 2, "shootingPctg": 0.0, "avgTimeOnIcePerGame": 630.0, "avgShiftsPerGame": 16.4, "faceoffWinPctg": 0.4651}, {"playerId": 8467370, "headshot": "https://assets.nhle.com/mugs/nhl/20032004/OTT/8467370.png", "firstName": {"default": "Mike"}, "lastName": {"default": "Fisher"}, "positionCode": "C", "gamesPlayed": 24, "goals": 4, "assists": 6, "points": 10, "plusMinus": -3, "penaltyMinutes": 39, "powerPlayGoals": 1, "shorthandedGoals": 0, "gameWinningGoals": 0, "overtimeGoals": 0, "shots": 47, "shootingPctg": 0.0851, "avgTimeOnIcePerGame": 1045.75, "avgShiftsPerGame": 24.6, "faceoffWinPctg": 0.4202}, {"playerId": 8467399, "headshot": "https://assets.nhle.com/mugs/nhl/20032004/OTT/8467399.png", "firstName": {"default": "Julien"}, "lastName": {"default": "Vauclair"}, "positionCode": "D", "gamesPlayed": 1, "goals": 0, "assists": 0, "points": 0, "plusMinus": 1, "penaltyMinutes": 2, "powerPlayGoals": 0, "shorthandedGoals": 0, "gameWinningGoals": 0, "overtimeGoals": 0, "shots": 0, "shootingPctg": 0.0, "avgTimeOnIcePerGame": 768.0, "avgShiftsPerGame": 19.0, "faceoffWinPctg": 0.0}, {"playerId": 8467425, "headshot": "https://assets.nhle.com/mugs/nhl/20032004/OTT/8467425.png", "firstName": {"default": "Petr"}, "lastName": {"default": "Schastlivy"}, "positionCode": "L", "gamesPlayed": 43, "goals": 2, "assists": 4, "points": 6, "plusMinus": -1, "penaltyMinutes": 14, "powerPlayGoals": 1, "shorthandedGoals": 0, "gameWinningGoals": 1, "overtimeGoals": 0, "shots": 37, "shootingPctg": 0.0541, "avgTimeOnIcePerGame": 571.7907, "avgShiftsPerGame": 14.0, "faceoffWinPctg": 0.4545}, {"playerId": 8467493, "headshot": "https://assets.nhle.com/mugs/nhl/20032004/OTT/8467493.png", "firstName": {"default": "Chris"}, "lastName": {"default": "Neil"}, "positionCode": "R", "gamesPlayed": 82, "goals": 8, "assists": 8, "points": 16, "plusMinus": 13, "penaltyMinutes": 194, "powerPlayGoals": 0, "shorthandedGoals": 0, "gameWinningGoals": 1, "overtimeGoals": 0, "shots": 76, "shootingPctg": 0.1053, "avgTimeOnIcePerGame": 530.8902, "avgShiftsPerGame": 13.3, "faceoffWinPctg": 0.4286}, {"playerId": 8467899, "headshot": "https://assets.nhle.com/mugs/nhl/20032004/OTT/8467899.png", "firstName": {"default": "Martin"}, "lastName": {"default": "Havlat", "cs": "Havl\u00e1t"}, "positionCode": "R", "gamesPlayed": 68, "goals": 31, "assists": 37, "points": 68, "plusMinus": 12, "penaltyMinutes": 46, "powerPlayGoals": 13, "shorthandedGoals": 0, "gameWinningGoals": 7, "overtimeGoals": 1, "shots": 175, "shootingPctg": 0.1771, "avgTimeOnIcePerGame": 1003.8971, "avgShiftsPerGame": 21.2, "faceoffWinPctg": 0.3636}, {"playerId": 8467967, "headshot": "https://assets.nhle.com/mugs/nhl/20032004/OTT/8467967.png", "firstName": {"default": "Chris"}, "lastName": {"default": "Kelly"}, "positionCode": "C", "gamesPlayed": 4, "goals": 0, "assists": 0, "points": 0, "plusMinus": -2, "penaltyMinutes": 0, "powerPlayGoals": 0, "shorthandedGoals": 0, "gameWinningGoals": 0, "overtimeGoals": 0, "shots": 4, "shootingPctg": 0.0, "avgTimeOnIcePerGame": 569.0, "avgShiftsPerGame": 15.3, "faceoffWinPctg": 0.4}, {"playerId": 8468427, "headshot": "https://assets.nhle.com/mugs/nhl/20032004/OTT/8468427.png", "firstName": {"default": "Brian"}, "lastName": {"default": "Pothier"}, "positionCode": "D", "gamesPlayed": 55, "goals": 2, "assists": 6, "points": 8, "plusMinus": 6, "penaltyMinutes": 24, "powerPlayGoals": 1, "shorthandedGoals": 0, "gameWinningGoals": 1, "overtimeGoals": 0, "shots": 78, "shootingPctg": 0.0256, "avgTimeOnIcePerGame": 1003.2182, "avgShiftsPerGame": 23.3, "faceoffWinPctg": 0.0}, {"playerId": 8468501, "headshot": "https://assets.nhle.com/mugs/nhl/20032004/OTT/8468501.png", "firstName": {"default": "Anton"}, "lastName": {"default": "Volchenkov"}, "positionCode": "D", "gamesPlayed": 19, "goals": 1, "assists": 2, "points": 3, "plusMinus": 1, "penaltyMinutes": 8, "powerPlayGoals": 0, "shorthandedGoals": 0, "gameWinningGoals": 0, "overtimeGoals": 0, "shots": 15, "shootingPctg": 0.0667, "avgTimeOnIcePerGame": 784.4737, "avgShiftsPerGame": 17.7, "faceoffWinPctg": 0.0}, {"playerId": 8468535, "headshot": "https://assets.nhle.com/mugs/nhl/20032004/OTT/8468535.png", "firstName": {"default": "Antoine"}, "lastName": {"default": "Vermette"}, "positionCode": "C", "gamesPlayed": 57, "goals": 7, "assists": 7, "points": 14, "plusMinus": 5, "penaltyMinutes": 16, "powerPlayGoals": 0, "shorthandedGoals": 1, "gameWinningGoals": 0, "overtimeGoals": 0, "shots": 63, "shootingPctg": 0.1111, "avgTimeOnIcePerGame": 719.4737, "avgShiftsPerGame": 18.2, "faceoffWinPctg": 0.44}, {"playerId": 8469455, "headshot": "https://assets.nhle.com/mugs/nhl/20032004/OTT/8469455.png", "firstName": {"default": "Jason"}, "lastName": {"default": "Spezza"}, "positionCode": "C", "gamesPlayed": 78, "goals": 22, "assists": 33, "points": 55, "plusMinus": 22, "penaltyMinutes": 71, "powerPlayGoals": 5, "shorthandedGoals": 0, "gameWinningGoals": 3, "overtimeGoals": 0, "shots": 142, "shootingPctg": 0.1549, "avgTimeOnIcePerGame": 878.2949, "avgShiftsPerGame": 19.4, "faceoffWinPctg": 0.477}, {"playerId": 8469639, "headshot": "https://assets.nhle.com/mugs/nhl/20032004/OTT/8469639.png", "firstName": {"default": "Brooks"}, "lastName": {"default": "Laich"}, "positionCode": "C", "gamesPlayed": 1, "goals": 0, "assists": 0, "points": 0, "plusMinus": 0, "penaltyMinutes": 2, "powerPlayGoals": 0, "shorthandedGoals": 0, "gameWinningGoals": 0, "overtimeGoals": 0, "shots": 1, "shootingPctg": 0.0, "avgTimeOnIcePerGame": 574.0, "avgShiftsPerGame": 14.0, "faceoffWinPctg": 0.4286}], "goalies": [{"playerId": 8459579, "headshot": "https://assets.nhle.com/mugs/nhl/20032004/OTT/8459579.png", "firstName": {"default": "Patrick"}, "lastName": {"default": "Lalime"}, "gamesPlayed": 57, "gamesStarted": 55, "wins": 25, "losses": 23, "ties": 7, "goalsAgainstAverage": 2.292177, "savePercentage": 0.904798, "shotsAgainst": 1334, "saves": 1207, "goalsAgainst": 127, "shutouts": 5, "goals": 0, "assists": 2, "points": 2, "penaltyMinutes": 17, "timeOnIce": 199461}, {"playerId": 8468037, "headshot": "https://assets.nhle.com/mugs/nhl/20032004/OTT/8468037.png", "firstName": {"default": "Martin"}, "lastName": {"default": "Prusek"}, "gamesPlayed": 29, "gamesStarted": 26, "wins": 16, "losses": 6, "ties": 3, "goalsAgainstAverage": 2.120928, "savePercentage": 0.917051, "shotsAgainst": 651, "saves": 597, "goalsAgainst": 54, "shutouts": 3, "goals": 0, "assists": 1, "points": 1, "penaltyMinutes": 0, "timeOnIce": 91658}, {"playerId": 8469548, "headshot": "https://assets.nhle.com/mugs/nhl/20032004/OTT/8469548.png", "firstName": {"default": "Ray"}, "lastName": {"default": "Emery"}, "gamesPlayed": 3, "gamesStarted": 1, "wins": 2, "losses": 0, "ties": 0, "goalsAgainstAverage": 2.377493, "savePercentage": 0.903846, "shotsAgainst": 52, "saves": 47, "goalsAgainst": 5, "shutouts": 0, "goals": 0, "assists": 0, "points": 0, "penaltyMinutes": 2, "timeOnIce": 7571}]}